{
  "columnHierarchy": {
    "epochs": [
      {
        "id": "epoch_1",
        "name": "Screening",
        "instanceType": "StudyEpoch",
        "type": {
          "id": "fad554a0-fbf5-4435-9088-0d8052c710f3",
          "code": "C98779",
          "codeSystem": "http://www.cdisc.org",
          "codeSystemVersion": "2024-09-27",
          "decode": "Screening Epoch",
          "instanceType": "Code"
        }
      },
      {
        "id": "epoch_2",
        "name": "Period 1",
        "instanceType": "StudyEpoch",
        "type": {
          "id": "716f705b-3c0c-42f5-b15f-7d941945f166",
          "code": "C98780",
          "codeSystem": "http://www.cdisc.org",
          "codeSystemVersion": "2024-09-27",
          "decode": "Treatment Epoch",
          "instanceType": "Code"
        }
      },
      {
        "id": "epoch_3",
        "name": "Wash out",
        "instanceType": "StudyEpoch",
        "type": {
          "id": "935264ec-59d6-4fd7-aece-84e5f45c4a02",
          "code": "C98780",
          "codeSystem": "http://www.cdisc.org",
          "codeSystemVersion": "2024-09-27",
          "decode": "Treatment Epoch",
          "instanceType": "Code"
        }
      },
      {
        "id": "epoch_4",
        "name": "Period 2",
        "instanceType": "StudyEpoch",
        "type": {
          "id": "71f0c240-ec78-4aa0-aaaf-27d9f1f5a6e1",
          "code": "C98780",
          "codeSystem": "http://www.cdisc.org",
          "codeSystemVersion": "2024-09-27",
          "decode": "Treatment Epoch",
          "instanceType": "Code"
        }
      },
      {
        "id": "epoch_5",
        "name": "Follow-up/ED",
        "instanceType": "StudyEpoch",
        "type": {
          "id": "54b27aa3-398a-4a8d-94f2-070aaffe9fdf",
          "code": "C98781",
          "codeSystem": "http://www.cdisc.org",
          "codeSystemVersion": "2024-09-27",
          "decode": "Follow-up Epoch",
          "instanceType": "Code"
        }
      },
      {
        "id": "epoch_6",
        "name": "Additional Follow-up for TE ADAa",
        "instanceType": "StudyEpoch",
        "type": {
          "id": "2c8acea2-3efe-498d-9183-41b73417068f",
          "code": "C98781",
          "codeSystem": "http://www.cdisc.org",
          "codeSystemVersion": "2024-09-27",
          "decode": "Follow-up Epoch",
          "instanceType": "Code"
        }
      }
    ],
    "encounters": [
      {
        "id": "enc_1",
        "name": "Screening (Days -28 to -2)",
        "instanceType": "Encounter",
        "type": {
          "id": "747136cb-bcb9-4c40-bb80-6c4e4b515b1a",
          "code": "C48262",
          "codeSystem": "http://www.cdisc.org",
          "codeSystemVersion": "2024-09-27",
          "decode": "Screening",
          "instanceType": "Code"
        },
        "epochId": "epoch_1"
      },
      {
        "id": "enc_2",
        "name": "Screening (Day -1)",
        "instanceType": "Encounter",
        "type": {
          "id": "b55cb56b-482e-42d6-83cb-89a85dc19bd7",
          "code": "C48262",
          "codeSystem": "http://www.cdisc.org",
          "codeSystemVersion": "2024-09-27",
          "decode": "Screening",
          "instanceType": "Code"
        },
        "epochId": "epoch_1"
      },
      {
        "id": "enc_3",
        "name": "Period 1 (Day 1)",
        "instanceType": "Encounter",
        "type": {
          "id": "32f8c55c-9e86-4844-9cc5-c60da98efba6",
          "code": "C82517",
          "codeSystem": "http://www.cdisc.org",
          "codeSystemVersion": "2024-09-27",
          "decode": "Baseline",
          "instanceType": "Code"
        },
        "epochId": "epoch_2"
      },
      {
        "id": "enc_4",
        "name": "Wash out (3 to 14 days)",
        "instanceType": "Encounter",
        "type": {
          "id": "ef42601f-333d-4a2a-8a83-99423ac8a9ac",
          "code": "C99156",
          "codeSystem": "http://www.cdisc.org",
          "codeSystemVersion": "2024-09-27",
          "decode": "Scheduled Visit",
          "instanceType": "Code"
        },
        "epochId": "epoch_3"
      },
      {
        "id": "enc_5",
        "name": "Period 2 (Day -1)",
        "instanceType": "Encounter",
        "type": {
          "id": "0b0137cd-9a99-4192-92c2-7eb6b66ff5a0",
          "code": "C99156",
          "codeSystem": "http://www.cdisc.org",
          "codeSystemVersion": "2024-09-27",
          "decode": "Scheduled Visit",
          "instanceType": "Code"
        },
        "epochId": "epoch_4"
      },
      {
        "id": "enc_6",
        "name": "Period 2 (Day 1)",
        "instanceType": "Encounter",
        "type": {
          "id": "216dde15-70d5-4701-bedf-4790e7fc0135",
          "code": "C82517",
          "codeSystem": "http://www.cdisc.org",
          "codeSystemVersion": "2024-09-27",
          "decode": "Baseline",
          "instanceType": "Code"
        },
        "epochId": "epoch_4"
      },
      {
        "id": "enc_7",
        "name": "Follow-up/ED (Within 28±2 days)",
        "instanceType": "Encounter",
        "type": {
          "id": "c6727679-a011-4d53-95b8-4b5608892677",
          "code": "C99158",
          "codeSystem": "http://www.cdisc.org",
          "codeSystemVersion": "2024-09-27",
          "decode": "Follow-up",
          "instanceType": "Code"
        },
        "epochId": "epoch_5"
      },
      {
        "id": "enc_8",
        "name": "Additional Follow-up for TE ADA",
        "instanceType": "Encounter",
        "type": {
          "id": "987ea106-b0e9-4dc2-9b91-6c4a44c110a7",
          "code": "C99158",
          "codeSystem": "http://www.cdisc.org",
          "codeSystemVersion": "2024-09-27",
          "decode": "Follow-up",
          "instanceType": "Code"
        },
        "epochId": "epoch_6"
      }
    ],
    "plannedTimepoints": [
      {
        "id": "pt_1",
        "visit": "Days -28 to -2",
        "epoch": "",
        "epochId": "",
        "day": "",
        "window": null,
        "encounterId": "enc_1",
        "instanceType": "Timing"
      },
      {
        "id": "pt_2",
        "visit": "Day -1",
        "epoch": "",
        "epochId": "",
        "day": "",
        "window": null,
        "encounterId": "enc_2",
        "instanceType": "Timing"
      },
      {
        "id": "pt_3",
        "visit": "Day 1",
        "epoch": "",
        "epochId": "",
        "day": "",
        "window": null,
        "encounterId": "enc_3",
        "instanceType": "Timing"
      },
      {
        "id": "pt_4",
        "visit": "3 to 14 days",
        "epoch": "",
        "epochId": "",
        "day": "",
        "window": null,
        "encounterId": "enc_4",
        "instanceType": "Timing"
      },
      {
        "id": "pt_5",
        "visit": "Day -1",
        "epoch": "",
        "epochId": "",
        "day": "",
        "window": null,
        "encounterId": "enc_5",
        "instanceType": "Timing"
      },
      {
        "id": "pt_6",
        "visit": "Day 1",
        "epoch": "",
        "epochId": "",
        "day": "",
        "window": null,
        "encounterId": "enc_6",
        "instanceType": "Timing"
      },
      {
        "id": "pt_7",
        "visit": "Within 28±2 days after last study treatment",
        "epoch": "",
        "epochId": "",
        "day": "",
        "window": null,
        "encounterId": "enc_7",
        "instanceType": "Timing"
      },
      {
        "id": "pt_8",
        "visit": "Additional Follow-up for TE ADAa",
        "epoch": "",
        "epochId": "",
        "day": "",
        "window": null,
        "encounterId": "enc_8",
        "instanceType": "Timing"
      }
    ]
  },
  "rowGroups": [
    {
      "id": "grp_1",
      "name": "Clinical Assessments",
      "description": null,
      "childIds": [],
      "instanceType": "Activity",
      "activityNames": [
        "Informed Consent",
        "Randomization",
        "Admission to CRU",
        "Discharge from CRU",
        "Medical History",
        "Collect Pre-existing Conditions and Adverse Events",
        "Physical Exam",
        "Height and Weight",
        "Collect Hypoglycemic Events",
        "Collect Concomitant Medications",
        "Meal",
        "Insulin infusion to Induce Hypoglycemia",
        "Bedside PG Monitoring for Safety",
        "Study Treatment Administration",
        "Injection-Site Assessment",
        "Nasal Inspection",
        "Vital Signs (Supine Blood Pressure, Pulse Rate, and Body Temperature)",
        "Single 12-lead ECG (Local)",
        "Triplicate 12-lead ECG (Central)"
      ]
    },
    {
      "id": "grp_2",
      "name": "Laboratory Tests",
      "description": null,
      "childIds": [],
      "instanceType": "Activity",
      "activityNames": [
        "Clinical Serology Tests",
        "Clinical Lab Tests (Hematology, Clinical Chemistry, and Urinalysis)",
        "HbA1c",
        "Pregnancy Test (Female patients of childbearing potential only)",
        "FSH (Female patients only)",
        "Ethanol Testing",
        "Urine Drug Screen",
        "PK (Glucagon)",
        "Plasma Glucose for PD",
        "Genetic Sample (Stored)",
        "Anti-glucagon Antibodies"
      ]
    },
    {
      "id": "grp_3",
      "name": "Health Outcome Instruments",
      "description": null,
      "childIds": [],
      "instanceType": "Activity",
      "activityNames": [
        "Clarke Hypoglycemia Awareness Survey",
        "Nasal and Non-nasal Score Questionnaire",
        "Edinburgh Hypoglycemia Scale: Experimental Hypoglycemia"
      ]
    }
  ],
  "footnotes": [
    "a. Samples for immunogenicity, should be collected every 12 weeks (84±7 days) until the titer returns to baseline (ie, returns to within a single 2-fold dilution of the baseline titer) or until 1 year after the last dose of study treatment. A time-matched PK (glucagon) sample may be collected at the follow-up immunogenicity assessment(s) if warranted and agreed upon between both the investigator and sponsor.",
    "Note: If multiple procedures take place at the same time point, the following order of the procedure should be used: ECG, vital signs, and venipuncture. Plasma glucose sample should be collected as close as possible of protocol-specified time point."
  ]
}