{
  "processing_issues": [
    {
      "phase": "execution_model",
      "issue_type": "warning",
      "message": "Could not resolve visit 'End of Study' to encounter ID",
      "is_known_limitation": false,
      "fallback_used": null,
      "details": {
        "visit_name": "End of Study",
        "available_encounters": [
          "Screening (Within 14 days)",
          "Randomization Call",
          "Leukapheresis (Within approx. 5 days)",
          "Conditioning Day -5",
          "Conditioning Day -4"
        ]
      }
    }
  ],
  "total_issues": 1,
  "known_limitations": 0,
  "visit_resolution_failures": 0,
  "epoch_resolution_failures": 0
}